paircraft/__init__.py
paircraft/client.py
paircraft/exceptions.py
paircraft/models.py
paircraft-1.0.0.dist-info/licenses/LICENSE
tests/__init__.py
tests/test_client.py
paircraft-1.0.0.dist-info/METADATA
paircraft-1.0.0.dist-info/WHEEL
paircraft-1.0.0.dist-info/top_level.txt
paircraft-1.0.0.dist-info/RECORD
