Metadata-Version: 2.4
Name: paircraft
Version: 1.0.0
Summary: Python SDK for the Paircraft API - Chess Tournament Management
Home-page: https://github.com/chughjug/ratings
Author: Paircraft
Author-email: Paircraft <support@paircraft.io>
License: MIT
Project-URL: Homepage, https://paircraft.io
Project-URL: Documentation, https://paircraft.io/api/docs
Project-URL: Repository, https://github.com/chughjug/ratings
Project-URL: Bug Tracker, https://github.com/chughjug/ratings/issues
Keywords: chess,tournament,api,sdk,swiss,pairing,uscf,fide,paircraft
Classifier: Development Status :: 4 - Beta
Classifier: Intended Audience :: Developers
Classifier: License :: OSI Approved :: MIT License
Classifier: Operating System :: OS Independent
Classifier: Programming Language :: Python :: 3
Classifier: Programming Language :: Python :: 3.8
Classifier: Programming Language :: Python :: 3.9
Classifier: Programming Language :: Python :: 3.10
Classifier: Programming Language :: Python :: 3.11
Classifier: Programming Language :: Python :: 3.12
Classifier: Topic :: Games/Entertainment :: Board Games
Requires-Python: >=3.8
License-File: LICENSE
Requires-Dist: requests>=2.25.0
Provides-Extra: dev
Requires-Dist: pytest>=6.0; extra == "dev"
Requires-Dist: pytest-cov>=2.0; extra == "dev"
Requires-Dist: black>=21.0; extra == "dev"
Requires-Dist: flake8>=3.9; extra == "dev"
Dynamic: author
Dynamic: home-page
Dynamic: license-file
Dynamic: requires-python
